<annotation>
	<folder>collectedimages</folder>
	<filename>Drink.06e04b71-baa2-11ed-95a6-308d99be8502.jpg</filename>
	<path>C:\Users\dell\Documents\RealTimeObjectDetection\Tensorflow\workspace\images\collectedimages\Drink.06e04b71-baa2-11ed-95a6-308d99be8502.jpg</path>
	<source>
		<database>Unknown</database>
	</source>
	<size>
		<width>640</width>
		<height>480</height>
		<depth>3</depth>
	</size>
	<segmented>0</segmented>
	<object>
		<name>drink</name>
		<pose>Unspecified</pose>
		<truncated>0</truncated>
		<difficult>0</difficult>
		<bndbox>
			<xmin>402</xmin>
			<ymin>70</ymin>
			<xmax>517</xmax>
			<ymax>206</ymax>
		</bndbox>
	</object>
</annotation>
