<annotation>
	<folder>collectedimages</folder>
	<filename>IMG_20200904_154249.jpg</filename>
	<path>C:\Users\HP-840\RealTimeObjectDetection\Tensorflow\workspace\images\collectedimages\IMG_20200904_154249.jpg</path>
	<source>
		<database>Unknown</database>
	</source>
	<size>
		<width>1387</width>
		<height>1916</height>
		<depth>3</depth>
	</size>
	<segmented>0</segmented>
	<object>
		<name>G</name>
		<pose>Unspecified</pose>
		<truncated>0</truncated>
		<difficult>0</difficult>
		<bndbox>
			<xmin>71</xmin>
			<ymin>119</ymin>
			<xmax>1286</xmax>
			<ymax>1878</ymax>
		</bndbox>
	</object>
</annotation>
