<annotation>
	<folder>collectedimages</folder>
	<filename>marry.18db6068-bb88-11ed-aaca-5cbaefaaf10e.jpg</filename>
	<path>D:\RealTimeObjectDetection\Tensorflow\workspace\images\collectedimages\marry.18db6068-bb88-11ed-aaca-5cbaefaaf10e.jpg</path>
	<source>
		<database>Unknown</database>
	</source>
	<size>
		<width>640</width>
		<height>480</height>
		<depth>3</depth>
	</size>
	<segmented>0</segmented>
	<object>
		<name>marry</name>
		<pose>Unspecified</pose>
		<truncated>1</truncated>
		<difficult>0</difficult>
		<bndbox>
			<xmin>86</xmin>
			<ymin>300</ymin>
			<xmax>623</xmax>
			<ymax>480</ymax>
		</bndbox>
	</object>
</annotation>
