<annotation>
	<folder>collectedimages</folder>
	<filename>mixer.30b7ae72-c81b-11ed-9521-5cbaefaaf10e.jpg</filename>
	<path>D:\RealTimeObjectDetection\Tensorflow\workspace\images\collectedimages\mixer.30b7ae72-c81b-11ed-9521-5cbaefaaf10e.jpg</path>
	<source>
		<database>Unknown</database>
	</source>
	<size>
		<width>640</width>
		<height>480</height>
		<depth>3</depth>
	</size>
	<segmented>0</segmented>
	<object>
		<name>mixer</name>
		<pose>Unspecified</pose>
		<truncated>0</truncated>
		<difficult>0</difficult>
		<bndbox>
			<xmin>145</xmin>
			<ymin>157</ymin>
			<xmax>476</xmax>
			<ymax>469</ymax>
		</bndbox>
	</object>
</annotation>
