<annotation>
	<folder>collectedimages</folder>
	<filename>muslim.e4da9902-c7a9-11ed-bc4e-5cbaefaaf10e.jpg</filename>
	<path>D:\RealTimeObjectDetection\Tensorflow\workspace\images\collectedimages\muslim.e4da9902-c7a9-11ed-bc4e-5cbaefaaf10e.jpg</path>
	<source>
		<database>Unknown</database>
	</source>
	<size>
		<width>640</width>
		<height>480</height>
		<depth>3</depth>
	</size>
	<segmented>0</segmented>
	<object>
		<name>muslim</name>
		<pose>Unspecified</pose>
		<truncated>0</truncated>
		<difficult>0</difficult>
		<bndbox>
			<xmin>143</xmin>
			<ymin>139</ymin>
			<xmax>365</xmax>
			<ymax>409</ymax>
		</bndbox>
	</object>
</annotation>
