<annotation>
	<folder>collectedimages</folder>
	<filename>obidient.70a57850-c817-11ed-80a1-5cbaefaaf10e.jpg</filename>
	<path>D:\RealTimeObjectDetection\Tensorflow\workspace\images\collectedimages\obidient.70a57850-c817-11ed-80a1-5cbaefaaf10e.jpg</path>
	<source>
		<database>Unknown</database>
	</source>
	<size>
		<width>640</width>
		<height>480</height>
		<depth>3</depth>
	</size>
	<segmented>0</segmented>
	<object>
		<name>obedient</name>
		<pose>Unspecified</pose>
		<truncated>0</truncated>
		<difficult>0</difficult>
		<bndbox>
			<xmin>227</xmin>
			<ymin>300</ymin>
			<xmax>599</xmax>
			<ymax>442</ymax>
		</bndbox>
	</object>
</annotation>
