<annotation>
	<folder>collectedimages</folder>
	<filename>question.9a676bfc-bb84-11ed-a83a-5cbaefaaf10e - Copy.jpg</filename>
	<path>D:\RealTimeObjectDetection\Tensorflow\workspace\images\collectedimages\question.9a676bfc-bb84-11ed-a83a-5cbaefaaf10e - Copy.jpg</path>
	<source>
		<database>Unknown</database>
	</source>
	<size>
		<width>640</width>
		<height>480</height>
		<depth>3</depth>
	</size>
	<segmented>0</segmented>
	<object>
		<name>question</name>
		<pose>Unspecified</pose>
		<truncated>0</truncated>
		<difficult>0</difficult>
		<bndbox>
			<xmin>281</xmin>
			<ymin>295</ymin>
			<xmax>601</xmax>
			<ymax>392</ymax>
		</bndbox>
	</object>
</annotation>
