<annotation>
	<folder>collectedimages</folder>
	<filename>walk.07b15679-c4ee-11ed-8117-5cbaefaaf10e - Copy.jpg</filename>
	<path>D:\RealTimeObjectDetection\Tensorflow\workspace\images\collectedimages\walk.07b15679-c4ee-11ed-8117-5cbaefaaf10e - Copy.jpg</path>
	<source>
		<database>Unknown</database>
	</source>
	<size>
		<width>640</width>
		<height>480</height>
		<depth>3</depth>
	</size>
	<segmented>0</segmented>
	<object>
		<name>walk</name>
		<pose>Unspecified</pose>
		<truncated>0</truncated>
		<difficult>0</difficult>
		<bndbox>
			<xmin>158</xmin>
			<ymin>278</ymin>
			<xmax>303</xmax>
			<ymax>451</ymax>
		</bndbox>
	</object>
</annotation>
